quickclone/__init__.py
quickclone/__main__.py
quickclone/local.py
quickclone/_app/__init__.py
quickclone/_app/qkln.py
quickclone/compatibility/__init__.py
quickclone/compatibility/v0_4_0.py
quickclone/compatibility/v0_6_0.py
quickclone/config/__init__.py
quickclone/config/cache.py
quickclone/config/common.py
quickclone/config/configurator.py
quickclone/config/defaults/example.toml
quickclone/config/defaults/quickclone.toml
quickclone/delegation/__init__.py
quickclone/delegation/errors.py
quickclone/delegation/tasks.py
quickclone/delegation/vcs/__init__.py
quickclone/delegation/vcs/common.py
quickclone/delegation/vcs/git.py
quickclone/delegation/vcs/mercurial.py
quickclone/remote/__init__.py
quickclone/remote/locators.py
quickclone/remote/parser.py
quickclone/remote/scp.py
quickclone-0.6.0.dist-info/LICENSE
quickclone-0.6.0.dist-info/METADATA
quickclone-0.6.0.dist-info/WHEEL
quickclone-0.6.0.dist-info/entry_points.txt
quickclone-0.6.0.dist-info/top_level.txt
quickclone-0.6.0.dist-info/RECORD
