Metadata-Version: 2.2
Name: quickclone
Version: 0.6.0
Summary: Command line utility for quickly cloning remote SCM repositories as succintly as possible.
Home-page: https://github.com/RenoirTan/QuickClone
Author: RenoirTan
Author-email: renoirtan2005@gmail.com
Classifier: Programming Language :: Python :: 3
Classifier: License :: OSI Approved :: GNU General Public License v3 or later (GPLv3+)
Classifier: Operating System :: OS Independent
Classifier: Intended Audience :: Developers
Classifier: Topic :: Software Development :: Version Control
Classifier: Topic :: Utilities
Requires-Python: >=3.7
License-File: LICENSE
Requires-Dist: toml>=0.10.2
